{"update_id":950521485,
"channel_post":{"message_id":54,"sender_chat":{"id":-1001425480795,"title":"Orena.uz | Biznes va texnologiyalar","username":"orenauz","type":"channel"},"chat":{"id":-1001425480795,"title":"Orena.uz | Biznes va texnologiyalar","username":"orenauz","type":"channel"},"date":1666099911,"photo":[{"file_id":"AgACAgIAAx0CVPccWwADNmNOqscpsgRBvrTguxohURyQGutUAAJOwjEbNWV5SisaHcYo-fyyAQADAgADcwADKgQ","file_unique_id":"AQADTsIxGzVleUp4","file_size":1021,"width":90,"height":50},{"file_id":"AgACAgIAAx0CVPccWwADNmNOqscpsgRBvrTguxohURyQGutUAAJOwjEbNWV5SisaHcYo-fyyAQADAgADbQADKgQ","file_unique_id":"AQADTsIxGzVleUpy","file_size":9513,"width":320,"height":178},{"file_id":"AgACAgIAAx0CVPccWwADNmNOqscpsgRBvrTguxohURyQGutUAAJOwjEbNWV5SisaHcYo-fyyAQADAgADeAADKgQ","file_unique_id":"AQADTsIxGzVleUp9","file_size":33578,"width":800,"height":444},{"file_id":"AgACAgIAAx0CVPccWwADNmNOqscpsgRBvrTguxohURyQGutUAAJOwjEbNWV5SisaHcYo-fyyAQADAgADeQADKgQ","file_unique_id":"AQADTsIxGzVleUp-","file_size":58883,"width":1280,"height":710}],"caption":"TikTok\u2019ning kunlik foydalanuvchilar soni 1 milliarddan oshdi\n\nSo\u2018nggi bir necha yil ichida Xitoyning TikTok video xizmati foydalanuvchilar orasida juda keng ommalashmoqda. Ayniqsa, boshqa mashhur brendlar uning uslubidan nusxa ko\u2018chira boshladi.\n\n\u201cScience and Technology Innovation Board Daily\u201d ma\u2019lumotiga ko\u2018ra, uning kunlik faol foydalanuvchilari hozirda 1 milliarddan oshadi. Shuningdek, kompaniya o\u2018z foydalanuvchilarini boshqarishda qiynalayotgani ma\u2019lum bo\u2018ldi.\n\nIlgari global kundalik foydalanuvchilari 1 milliarddan oshadigan atigi to\u2018rtta ilova mavjud edi. Bular Facebook, WhatsApp, Instagram va YouTube.\n\nKanalimizdagi yangiliklarni kuzatib boring\ud83d\udc47\n\n\ud83d\udc49 @orenauz \u2013 biznes va texnologiyalar","caption_entities":[{"offset":0,"length":60,"type":"bold"},{"offset":107,"length":1,"type":"text_link","url":"https://t.me/orenauz"},{"offset":226,"length":1,"type":"text_link","url":"https://t.me/orenauz"},{"offset":295,"length":11,"type":"text_link","url":"https://www.google.com/amp/s/www.gizchina.com/2022/10/18/tiktok-global-daily-activity-exceeds-the-1-billion-mark/amp/"},{"offset":371,"length":1,"type":"text_link","url":"https://t.me/orenauz"},{"offset":616,"length":49,"type":"bold"},{"offset":665,"length":8,"type":"mention"},{"offset":665,"length":8,"type":"bold"},{"offset":674,"length":26,"type":"bold"}]}}